{"사과":38,"바나나":9,"포도":8,"딸기":23,"수박":34,"복숭아":37,"망고":14,"레몬":9,"오렌지":30,"키위":20,"파인애플":33,"체리":19,"블루베리":36,"라즈베리":14,"멜론":30,"감":37,"배":37,"자두":15,"살구":38,"귤":7,"라임":19,"코코넛":22,"아보카도":35,"무화과":10,"두리안":39,"리치":18,"구아바":5,"파파야":23,"패션후르츠":26,"대추":31,"석류":12,"크랜베리":14,"블랙베리":20,"복분자":19,"산딸기":13,"매실":25,"모과":8,"유자":15,"당근":28,"양파":28,"감자":17,"고구마":34,"오이":11,"토마토":22,"배추":13,"시금치":23,"브로콜리":32,"양배추":8,"파프리카":17,"가지":23,"호박":5,"무":17,"파":20,"마늘":13,"생강":10,"고추":34,"부추":34,"상추":25,"깻잎":35,"미나리":27,"도라지":13,"더덕":7,"버섯":28,"연근":24,"콩":22,"팥":10,"옥수수":14,"아스파라거스":14,"셀러리":21,"레터스":16,"비트":28,"래디시":36,"청경채":7,"쑥갓":17,"방울토마토":5,"새싹채소":15,"하늘":16,"구름":36,"바람":35,"비":16,"눈":6,"태양":35,"달":19,"별":37,"무지개":6,"번개":29,"천둥":35,"안개":18,"서리":9,"우박":6,"폭풍":23,"폭설":23,"태풍":29,"가뭄":26,"홍수":5,"지진":8,"화산":13,"쓰나미":7,"황사":11,"미세먼지":13,"이슬":34,"서늘함":17,"바다":8,"산":37,"강":22,"숲":26,"꽃":5,"나무":14,"풀":27,"돌":28,"모래":20,"흙":17,"호수":25,"폭포":12,"섬":39,"사막":18,"평원":6,"계곡":31,"절벽":24,"동굴":23,"해변":25,"늪":17,"습지":13,"갯벌":15,"고원":11,"분지":40,"저수지":15,"연못":16,"시내":19,"개울":27,"봉우리":17,"능선":30,"협곡":11,"빙하":33,"오아시스":7,"초원":28,"고양이":24,"강아지":39,"토끼":26,"곰":28,"사자":5,"호랑이":19,"코끼리":18,"기린":15,"원숭이":13,"늑대":24,"여우":28,"돼지":35,"소":14,"말":35,"양":13,"닭":16,"오리":38,"판다":5,"하마":23,"치타":13,"표범":24,"재규어":29,"퓨마":21,"스라소니":14,"너구리":33,"오소리":37,"족제비":32,"다람쥐":34,"청설모":7,"쥐":21,"두더지":17,"고슴도치":17,"사슴":9,"노루":25,"멧돼지":36,"들소":5,"얼룩말":11,"코뿔소":10,"낙타":24,"라마":32,"알파카":15,"염소":21,"당나귀":7,"노새":22,"버팔로":13,"순록":18,"독수리":21,"참새":25,"비둘기":24,"까마귀":18,"까치":20,"갈매기":21,"펭귄":17,"타조":7,"공작":9,"앵무새":29,"올빼미":26,"부엉이":29,"황새":37,"두루미":6,"백조":28,"거위":34,"플라밍고":15,"펠리컨":32,"딱따구리":11,"제비":26,"종달새":28,"박새":9,"찌르레기":35,"나비":33,"벌":12,"개미":20,"물고기":13,"고래":8,"상어":37,"거북이":10,"뱀":22,"개구리":30,"악어":6,"문어":33,"오징어":8,"새우":29,"게":7,"랍스터":26,"조개":32,"굴":33,"홍합":5,"해파리":10,"불가사리":23,"해마":32,"가오리":20,"돌고래":5,"바다표범":11,"바다코끼리":16,"연어":19,"참치":26,"고등어":21,"갈치":15,"전갱이":4,"도미":11,"복어":1,"잠자리":14,"사마귀":9,"메뚜기":22,"귀뚜라미":23,"반딧불이":12,"무당벌레":31,"행복":20,"사랑":20,"희망":34,"꿈":22,"자유":33,"평화":30,"용기":17,"지혜":40,"슬픔":16,"기쁨":23,"분노":12,"두려움":26,"놀람":21,"설렘":13,"그리움":30,"외로움":32,"믿음":40,"신뢰":33,"존중":19,"감사":11,"용서":38,"인내":18,"겸손":13,"성실":16,"열정":33,"의지":15,"집념":8,"포기":36,"후회":22,"반성":25,"긍정":36,"부정":32,"불안":24,"걱정":16,"스트레스":38,"여유":19,"편안":35,"흥분":29,"당혹":16,"부끄러움":8,"자신감":5,"열등감":40,"우월감":34,"공감":25,"연민":13,"죄책감":32,"자부심":13,"커피":6,"차":30,"물":27,"우유":26,"주스":8,"맥주":37,"와인":12,"콜라":21,"사이다":5,"소주":32,"막걸리":8,"녹차":18,"홍차":27,"아메리카노":36,"라테":19,"에스프레소":23,"카푸치노":32,"모카":29,"아이스티":16,"레모네이드":9,"스무디":26,"밀크티":27,"코코아":33,"탄산수":25,"이온음료":40,"에너지드링크":14,"유자차":31,"생강차":37,"보리차":14,"밥":32,"김치":18,"불고기":18,"갈비":39,"떡볶이":9,"라면":11,"순두부":26,"비빔밥":11,"냉면":40,"삼겹살":38,"된장찌개":32,"김치찌개":6,"순대":10,"보쌈":27,"족발":27,"삼계탕":32,"설렁탕":18,"곰탕":33,"떡국":28,"잡채":38,"전":40,"빈대떡":6,"해물파전":35,"김밥":33,"주먹밥":38,"쌈":13,"나물":16,"무침":22,"볶음밥":6,"덮밥":27,"국밥":21,"육개장":21,"동태찌개":22,"부대찌개":38,"된장국":32,"미역국":28,"콩나물국":22,"시금치무침":5,"빵":11,"케이크":12,"피자":24,"햄버거":8,"초콜릿":10,"사탕":11,"국수":19,"파스타":28,"치킨":29,"스테이크":14,"샐러드":32,"스프":16,"스시":30,"타코":19,"부리토":17,"카레":25,"팟타이":32,"쌀국수":25,"딤섬":5,"만두":21,"교자":31,"춘권":35,"탕수육":32,"짜장면":25,"짬뽕":39,"마파두부":10,"오므라이스":15,"돈가스":14,"나폴리탄":23,"클램차우더":3,"아이스크림":31,"도넛":20,"쿠키":20,"파이":8,"과자":19,"젤리":12,"떡":36,"경단":6,"팥빙수":12,"호떡":27,"붕어빵":15,"타르트":15,"마카롱":19,"크루아상":22,"베이글":22,"머핀":36,"와플":36,"팬케이크":6,"크레페":11,"푸딩":26,"마시멜로":8,"된장":55,"간장":79,"고추장":56,"쌀":90,"밀가루":73,"설탕":95,"소금":59,"후추":84,"식초":74,"참기름":57,"들기름":55,"올리브유":71,"마요네즈":60,"케첩":65,"머스터드":6,"책":21,"음악":9,"영화":20,"게임":9,"여행":29,"운동":13,"요리":30,"그림":13,"사진":35,"드라마":21,"소설":25,"시":30,"춤":34,"노래":16,"악기":29,"연극":37,"뮤지컬":37,"콘서트":36,"전시":6,"독서":14,"글쓰기":10,"낚시":32,"캠핑":24,"등산":38,"수영":9,"달리기":10,"자전거":28,"요가":7,"명상":11,"테니스":15,"골프":30,"볼링":9,"배드민턴":16,"탁구":21,"당구":32,"포커":40,"체스":21,"바둑":15,"장기":34,"퍼즐":18,"보드게임":11,"레고":17,"모형":11,"수집":9,"만화":35,"웹툰":6,"애니메이션":32,"코딩":37,"블로그":13,"유튜브":14,"팟캐스트":28,"스트리밍":12,"독서모임":22,"피아노":27,"기타":25,"바이올린":12,"드럼":25,"플루트":33,"첼로":7,"트럼펫":6,"색소폰":31,"클라리넷":8,"하프":33,"우쿨렐레":25,"베이스":10,"신디사이저":11,"아코디언":27,"하모니카":12,"비파":35,"가야금":25,"거문고":35,"해금":12,"대금":18,"축구":20,"야구":28,"농구":20,"배구":9,"육상":32,"체조":22,"유도":29,"태권도":35,"권투":31,"레슬링":37,"씨름":31,"펜싱":36,"사격":17,"양궁":36,"다이빙":21,"서핑":14,"스키":12,"스노보드":22,"아이스하키":13,"피겨스케이팅":29,"마라톤":31,"철인3종":20,"트라이애슬론":17,"클라이밍":31,"격투기":8,"무술":13,"축구공":18,"야구방망이":8,"농구공":11,"배구공":25,"라켓":13,"골프채":23,"헬멧":12,"봄":40,"여름":34,"가을":22,"겨울":12,"아침":13,"점심":22,"저녁":16,"밤":23,"오전":20,"오후":26,"새벽":6,"황혼":15,"일출":38,"일몰":8,"주말":38,"평일":5,"월요일":35,"화요일":34,"수요일":39,"목요일":26,"금요일":40,"토요일":27,"일요일":40,"1월":22,"2월":7,"3월":23,"4월":2,"5월":7,"6월":6,"7월":18,"8월":13,"9월":9,"10월":3,"11월":25,"12월":19,"올해":18,"작년":26,"내년":10,"지금":37,"과거":13,"미래":6,"현재":28,"순간":32,"시간":5,"분":1,"초":19,"시대":15,"세기":13,"연대":25,"역사":10,"도시":19,"마을":7,"집":15,"학교":25,"회사":22,"병원":36,"공원":28,"시장":18,"주택":39,"아파트":31,"빌라":14,"오피스텔":15,"건물":31,"방":20,"거실":15,"부엌":38,"욕실":8,"침실":20,"베란다":28,"창문":5,"문":7,"계단":9,"엘리베이터":39,"주차장":36,"식당":26,"카페":32,"은행":21,"마트":33,"백화점":17,"서점":38,"도서관":27,"영화관":5,"공항":23,"역":16,"항구":30,"놀이터":6,"운동장":5,"수영장":21,"헬스장":27,"미용실":7,"체육관":11,"경기장":23,"박물관":7,"미술관":25,"과학관":16,"동물원":26,"식물원":36,"수족관":20,"놀이공원":11,"유원지":22,"캠프장":7,"야영장":3,"스키장":22,"골프장":4,"법원":7,"경찰서":5,"소방서":11,"우체국":23,"세무서":15,"구청":7,"시청":27,"국회":40,"대사관":1,"호텔":24,"모텔":14,"민박":25,"게스트하우스":15,"리조트":32,"펜션":27,"자동차":22,"기차":23,"비행기":10,"버스":16,"지하철":36,"택시":17,"오토바이":20,"트럭":37,"도로":26,"신호등":30,"교통":23,"운전":10,"고속도로":29,"터널":16,"교량":27,"육교":20,"횡단보도":14,"주유소":30,"세차장":12,"정류장":34,"플랫폼":17,"헬기":12,"열기구":22,"드론":19,"유람선":9,"페리":11,"잠수함":2,"수상스키":6,"킥보드":21,"전동차":19,"케이블카":19,"모노레일":12,"트램":25,"컴퓨터":33,"스마트폰":21,"카메라":39,"텔레비전":15,"냉장고":34,"세탁기":11,"에어컨":10,"시계":25,"노트북":38,"태블릿":27,"이어폰":32,"스피커":40,"충전기":26,"키보드":33,"마우스":13,"프린터":13,"스캐너":14,"모니터":18,"라우터":7,"서버":11,"클라우드":9,"인터넷":22,"와이파이":25,"블루투스":38,"USB":13,"하드디스크":5,"메모리":24,"배터리":29,"전원":8,"소프트웨어":25,"앱":40,"프로그램":12,"인공지능":29,"로봇":40,"스마트워치":13,"VR기기":3,"게임기":24,"콘솔":19,"믹서":18,"전자레인지":15,"밥솥":39,"청소기":9,"공기청정기":14,"가습기":33,"제습기":2,"빨간색":15,"파란색":5,"노란색":25,"초록색":12,"보라색":13,"주황색":10,"흰색":40,"검은색":35,"분홍색":36,"하늘색":33,"갈색":23,"회색":31,"금색":17,"은색":38,"베이지":16,"청록색":6,"연두색":29,"자주색":5,"남색":9,"진홍색":10,"주홍색":9,"올리브색":22,"민트색":26,"코랄색":19,"라벤더색":22,"아이보리":26,"카키색":8,"머스터드색":20,"가족":31,"친구":31,"부모":27,"어머니":10,"아버지":21,"형제":40,"자매":15,"아이":14,"할머니":26,"할아버지":17,"아들":23,"딸":17,"남편":24,"아내":39,"선생님":13,"학생":12,"의사":23,"간호사":31,"경찰":19,"소방관":19,"요리사":5,"운전기사":7,"배우":32,"가수":19,"직장":1,"동료":29,"상사":13,"사장":14,"직원":13,"이웃":35,"손님":35,"친척":7,"연인":35,"애인":8,"파트너":13,"짝":2,"스승":14,"제자":24,"선배":26,"후배":24,"지인":8,"낯선사람":24,"외국인":16,"노인":34,"어른":24,"청년":21,"청소년":17,"어린이":33,"변호사":29,"교사":17,"약사":14,"한의사":4,"치과의사":29,"수의사":26,"엔지니어":32,"개발자":25,"디자이너":34,"기획자":22,"마케터":22,"영업자":17,"회계사":32,"건축가":36,"인테리어":25,"조경사":18,"경찰관":11,"군인":26,"공무원":26,"기자":17,"아나운서":16,"작가":22,"시인":10,"화가":21,"조각가":23,"사진작가":9,"댄서":22,"코미디언":7,"감독":13,"작곡가":12,"프로듀서":26,"파티시에":31,"바리스타":20,"소믈리에":15,"웨이터":10,"셰프":24,"농부":9,"어부":36,"목수":20,"용접공":2,"배관공":3,"전기기사":2,"미용사":24,"택배기사":10,"버스기사":7,"파일럿":29,"선장":13,"기관사":15,"코":19,"입":25,"귀":27,"손":30,"발":33,"머리":11,"얼굴":6,"팔":25,"다리":14,"등":32,"어깨":20,"목":36,"허리":10,"가슴":17,"심장":37,"뇌":19,"뼈":36,"근육":34,"피부":36,"머리카락":33,"손가락":29,"발가락":9,"손목":25,"발목":19,"무릎":5,"팔꿈치":39,"손바닥":5,"발바닥":19,"눈썹":13,"속눈썹":24,"이마":7,"턱":5,"뺨":22,"광대":2,"코끝":2,"입술":29,"잇몸":8,"혀":18,"폐":31,"간":7,"위":30,"신장":18,"방광":11,"췌장":1,"비장":12,"척추":27,"혈관":6,"신경":3,"혈액":24,"림프":1,"호르몬":7,"세포":6,"유전자":15,"티셔츠":40,"셔츠":24,"블라우스":23,"바지":17,"청바지":18,"반바지":38,"치마":8,"원피스":35,"재킷":33,"코트":34,"점퍼":39,"패딩":14,"니트":21,"가디건":13,"조끼":26,"정장":16,"넥타이":14,"벨트":12,"양말":33,"스타킹":12,"신발":32,"운동화":38,"구두":9,"샌들":29,"슬리퍼":36,"부츠":22,"모자":34,"베레모":13,"야구모자":7,"선글라스":6,"안경":31,"가방":37,"백팩":12,"핸드백":17,"지갑":16,"반지":33,"목걸이":6,"팔찌":36,"귀걸이":24,"장갑":13,"스카프":15,"머플러":35,"수영복":26,"잠옷":20,"속옷":10,"양복":30,"수학":30,"영어":12,"국어":17,"과학":21,"지리":14,"철학":18,"심리학":29,"경제학":39,"사회학":22,"문학":36,"물리":39,"화학":34,"생물":10,"지구과학":7,"천문학":10,"의학":18,"법학":34,"경영학":28,"교육학":16,"언어학":26,"통계학":18,"컴퓨터공학":10,"건축학":30,"예술학":14,"음악학":20,"체육학":25,"영양학":36,"환경학":14,"교과서":7,"노트":12,"연필":8,"볼펜":39,"지우개":27,"자":19,"컴퍼스":7,"가위":26,"테이프":2,"책상":35,"칠판":1,"분필":6,"시험":36,"숙제":25,"업무":8,"회의":16,"출근":10,"퇴근":40,"야근":21,"월급":15,"보너스":7,"휴가":9,"프로젝트":7,"기획":30,"보고서":6,"발표":35,"브레인스토밍":13,"마감":23,"납기":17,"계약":29,"협상":29,"제안서":20,"견적":11,"인보이스":12,"결재":24,"승인":2,"반려":1,"채용":13,"면접":8,"이력서":40,"자기소개서":20,"인턴":28,"신입":32,"경력":32,"정치":18,"경제":36,"사회":19,"문화":23,"기술":14,"예술":17,"민주주의":26,"자본주의":22,"사회주의":15,"공산주의":13,"자유주의":1,"보수주의":20,"선거":6,"투표":8,"정부":15,"대통령":13,"총리":3,"장관":3,"국회의원":15,"세금":40,"복지":32,"의료":13,"교육":21,"안보":39,"외교":14,"통일":32,"법":22,"헌법":21,"형법":14,"민법":23,"재판":6,"검사":19,"판사":32,"환경":5,"기후":13,"온난화":10,"탄소":17,"오염":21,"재활용":23,"에너지":6,"태양광":9,"풍력":19,"수력":10,"원자력":4,"화석연료":6,"석유":16,"천연가스":24,"석탄":13,"생태계":16,"생물다양성":6,"멸종":20,"보존":15,"복원":8,"산림":1,"해양":6,"대기":1,"레스토랑":22,"패스트푸드":19,"뷔페":4,"포장마차":23,"분식점":25,"술집":13,"바":5,"베이커리":21,"아이스크림가게":20,"편의점":1,"슈퍼마켓":9,"공":10,"골대":1,"바둑판":13,"장기판":12,"체스판":16,"주사위":15,"카드":28,"블록":15,"퍼즐조각":16,"인형":14,"장난감":12,"조이스틱":25,"소파":26,"침대":39,"의자":18,"옷장":7,"서랍장":22,"선반":18,"테이블":10,"식탁":22,"커튼":12,"카펫":14,"러그":40,"조명":9,"샹들리에":4,"화분":26,"액자":32,"거울":37,"전화기":8,"팩스":9,"달력":23,"메모판":25,"수건":25,"이불":19,"베개":39,"담요":40,"쿠션":40,"칫솔":14,"치약":29,"비누":33,"샴푸":17,"린스":25,"로션":15,"선크림":9,"화장품":22,"향수":19,"면도기":23,"드라이어":13,"빗":38,"헤어핀":24,"고무줄":11,"손거울":16,"세면대":13,"변기":22,"욕조":14,"샤워기":25,"냄비":25,"프라이팬":26,"그릇":13,"컵":24,"접시":14,"젓가락":16,"숟가락":23,"포크":30,"칼":29,"도마":20,"개수대":25,"주전자":21,"커피메이커":24,"토스터":29,"오븐":11,"장미":38,"튤립":14,"국화":34,"해바라기":13,"벚꽃":26,"개나리":15,"진달래":22,"수선화":27,"라벤더":12,"카네이션":8,"백합":40,"아이리스":20,"모란":15,"작약":30,"코스모스":17,"선인장":15,"대나무":11,"소나무":33,"참나무":12,"단풍나무":38,"은행나무":19,"자작나무":15,"야자나무":7,"올리브나무":20,"뽕나무":1,"감나무":15,"사과나무":21,"배나무":13,"잔디":19,"이끼":27,"고사리":34,"양치류":6,"해조류":18,"매화":28,"오동나무":22,"건강":26,"질병":39,"감기":5,"독감":23,"코로나":8,"암":5,"당뇨":16,"고혈압":5,"심장병":19,"뇌졸중":12,"골절":22,"염좌":5,"알레르기":16,"아토피":6,"천식":12,"수술":37,"치료":35,"약":23,"주사":36,"진단":39,"처방":5,"입원":15,"재활":38,"물리치료":40,"한방":17,"침":18,"한약":4,"예방접종":18,"마스크":16,"혈압":32,"혈당":27,"체온":36,"맥박":23,"호흡":3,"면역":27,"전화":38,"문자":12,"이메일":5,"카카오톡":7,"인스타그램":14,"페이스북":21,"트위터":2,"틱톡":1,"넷플릭스":9,"라디오":19,"신문":8,"잡지":18,"뉴스":37,"광고":10,"방송":40,"채널":6,"콘텐츠":13,"돈":27,"저축":19,"투자":40,"주식":24,"부동산":25,"펀드":12,"보험":38,"대출":14,"현금":11,"계좌":5,"이자":35,"이윤":5,"손실":14,"예산":39,"지출":10,"수입":20,"부채":7,"자산":25,"환율":36,"물가":37,"인플레이션":24,"경기":6,"불황":29,"호황":32,"성장":14,"발전":32,"번영":4,"적자":9,"흑자":23,"관광":23,"숙소":23,"비행기표":8,"여권":33,"짐":24,"캐리어":9,"지도":7,"관광지":36,"명소":9,"유적지":19,"쇼핑":5,"음식투어":13,"맛집":12,"카페투어":7,"기념품":39,"환전":40,"한복":29,"한옥":39,"한식":20,"풍물":26,"사물놀이":19,"제기차기":21,"팽이":6,"연날리기":14,"강강술래":16,"판소리":5,"전통춤":13,"탈춤":34,"장승":3,"솟대":10,"토우":11,"도자기":37,"단오":37,"추석":30,"설날":19,"정월대보름":21,"동지":24,"K팝":19,"한류":22,"아이돌":19,"먹방":8,"BTS":13,"방탄소년단":12,"블랙핑크":10,"방탄":13,"SM":1,"JYP":8,"YG":5,"한국":21,"미국":10,"일본":18,"중국":10,"영국":14,"프랑스":9,"독일":7,"이탈리아":5,"스페인":22,"러시아":38,"캐나다":9,"호주":15,"인도":32,"브라질":22,"멕시코":1,"태국":20,"베트남":13,"인도네시아":4,"필리핀":21,"싱가포르":21,"말레이시아":22,"서울":38,"부산":33,"제주":40,"인천":15,"대구":6,"광주":12,"대전":21,"울산":20,"도쿄":27,"뉴욕":21,"런던":24,"파리":28,"베이징":27,"상하이":8,"홍콩":15,"방콕":10,"우주":31,"지구":9,"태양계":32,"은하":37,"블랙홀":10,"행성":32,"위성":29,"혜성":6,"소행성":21,"중력":24,"빛":19,"공간":15,"물질":19,"원자":31,"분자":14,"전자":11,"양성자":22,"중성자":7,"힉스입자":10,"양자역학":24,"상대성이론":18,"종교":12,"불교":25,"기독교":16,"이슬람":14,"유교":23,"도교":15,"힌두교":14,"신":25,"기도":6,"깨달음":21,"진리":5,"선":25,"악":29,"윤리":14,"도덕":8,"가치":39,"의미":5,"목적":8,"존재":9,"의식":10,"자아":5,"날씨":40,"온도":40,"계획":14,"약속":27,"기억":34,"생각":11,"느낌":24,"경험":23,"습관":35,"취미":34,"목표":31,"성공":19,"실패":15,"도전":11,"변화":30,"결정":10,"선택":29,"행동":19,"결과":29,"원인":21,"이유":27,"방법":15,"과정":26,"시작":26,"끝":27,"중간":4,"처음":12,"마지막":24,"반복":9,"패턴":20,"규칙":31,"광장":16,"골목":25,"지하":23,"지상":6,"지붕":35,"벽":24,"바닥":14,"천장":22,"기둥":27,"난간":7,"발코니":28,"테라스":13,"정원":39,"마당":11,"창고":35}