{"사과":16,"바나나":14,"포도":10,"딸기":39,"수박":38,"복숭아":5,"망고":11,"레몬":20,"오렌지":10,"키위":33,"파인애플":9,"체리":10,"블루베리":27,"라즈베리":12,"멜론":7,"감":28,"배":5,"자두":34,"살구":32,"귤":37,"라임":7,"코코넛":17,"아보카도":21,"무화과":22,"두리안":9,"리치":36,"구아바":36,"파파야":7,"패션후르츠":25,"대추":29,"석류":24,"크랜베리":17,"블랙베리":32,"복분자":30,"산딸기":30,"매실":8,"모과":6,"유자":21,"당근":34,"양파":27,"감자":10,"고구마":33,"오이":10,"토마토":21,"배추":22,"시금치":31,"브로콜리":13,"양배추":28,"파프리카":11,"가지":19,"호박":23,"무":27,"파":13,"마늘":32,"생강":37,"고추":39,"부추":36,"상추":15,"깻잎":36,"미나리":25,"도라지":23,"더덕":31,"버섯":22,"연근":8,"콩":8,"팥":13,"옥수수":36,"아스파라거스":29,"셀러리":5,"레터스":25,"비트":20,"래디시":11,"청경채":16,"쑥갓":10,"방울토마토":6,"새싹채소":8,"하늘":36,"구름":10,"바람":15,"비":35,"눈":8,"태양":33,"달":13,"별":40,"무지개":29,"번개":24,"천둥":30,"안개":38,"서리":5,"우박":22,"폭풍":10,"폭설":27,"태풍":31,"가뭄":19,"홍수":37,"지진":16,"화산":18,"쓰나미":25,"황사":19,"미세먼지":11,"이슬":22,"서늘함":10,"바다":36,"산":16,"강":10,"숲":12,"꽃":14,"나무":5,"풀":24,"돌":23,"모래":16,"흙":5,"호수":12,"폭포":17,"섬":26,"사막":22,"평원":17,"계곡":17,"절벽":29,"동굴":29,"해변":11,"늪":31,"습지":17,"갯벌":26,"고원":22,"분지":29,"저수지":14,"연못":29,"시내":40,"개울":8,"봉우리":21,"능선":7,"협곡":35,"빙하":38,"오아시스":35,"초원":34,"고양이":16,"강아지":15,"토끼":37,"곰":9,"사자":14,"호랑이":36,"코끼리":26,"기린":5,"원숭이":9,"늑대":39,"여우":40,"돼지":7,"소":38,"말":39,"양":30,"닭":32,"오리":17,"판다":9,"하마":28,"치타":36,"표범":38,"재규어":33,"퓨마":35,"스라소니":20,"너구리":12,"오소리":30,"족제비":28,"다람쥐":16,"청설모":27,"쥐":20,"두더지":13,"고슴도치":14,"사슴":21,"노루":6,"멧돼지":30,"들소":25,"얼룩말":25,"코뿔소":40,"낙타":29,"라마":26,"알파카":14,"염소":26,"당나귀":25,"노새":37,"버팔로":18,"순록":7,"독수리":25,"참새":37,"비둘기":12,"까마귀":15,"까치":29,"갈매기":12,"펭귄":39,"타조":26,"공작":25,"앵무새":39,"올빼미":5,"부엉이":7,"황새":13,"두루미":26,"백조":21,"거위":12,"플라밍고":31,"펠리컨":28,"딱따구리":31,"제비":10,"종달새":22,"박새":21,"찌르레기":16,"나비":22,"벌":10,"개미":28,"물고기":8,"고래":25,"상어":28,"거북이":40,"뱀":22,"개구리":34,"악어":30,"문어":33,"오징어":37,"새우":29,"게":38,"랍스터":31,"조개":32,"굴":35,"홍합":9,"해파리":31,"불가사리":36,"해마":28,"가오리":8,"돌고래":32,"바다표범":24,"바다코끼리":8,"연어":15,"참치":32,"고등어":30,"갈치":17,"전갱이":3,"도미":15,"복어":11,"잠자리":19,"사마귀":24,"메뚜기":6,"귀뚜라미":32,"반딧불이":37,"무당벌레":38,"행복":39,"사랑":32,"희망":10,"꿈":29,"자유":22,"평화":17,"용기":19,"지혜":15,"슬픔":23,"기쁨":9,"분노":15,"두려움":27,"놀람":6,"설렘":8,"그리움":32,"외로움":15,"믿음":16,"신뢰":35,"존중":15,"감사":40,"용서":36,"인내":24,"겸손":36,"성실":30,"열정":37,"의지":26,"집념":16,"포기":38,"후회":21,"반성":9,"긍정":9,"부정":36,"불안":36,"걱정":9,"스트레스":8,"여유":16,"편안":26,"흥분":11,"당혹":23,"부끄러움":40,"자신감":13,"열등감":22,"우월감":36,"공감":28,"연민":7,"죄책감":27,"자부심":38,"커피":34,"차":13,"물":34,"우유":5,"주스":37,"맥주":18,"와인":11,"콜라":40,"사이다":34,"소주":25,"막걸리":30,"녹차":29,"홍차":15,"아메리카노":14,"라테":39,"에스프레소":27,"카푸치노":20,"모카":34,"아이스티":13,"레모네이드":10,"스무디":39,"밀크티":8,"코코아":15,"탄산수":10,"이온음료":33,"에너지드링크":8,"유자차":8,"생강차":20,"보리차":22,"밥":20,"김치":39,"불고기":36,"갈비":40,"떡볶이":22,"라면":23,"순두부":27,"비빔밥":12,"냉면":24,"삼겹살":40,"된장찌개":15,"김치찌개":22,"순대":27,"보쌈":7,"족발":25,"삼계탕":16,"설렁탕":7,"곰탕":15,"떡국":5,"잡채":25,"전":34,"빈대떡":19,"해물파전":30,"김밥":35,"주먹밥":5,"쌈":5,"나물":18,"무침":39,"볶음밥":13,"덮밥":35,"국밥":11,"육개장":18,"동태찌개":11,"부대찌개":8,"된장국":13,"미역국":17,"콩나물국":14,"시금치무침":22,"빵":30,"케이크":24,"피자":31,"햄버거":11,"초콜릿":13,"사탕":25,"국수":18,"파스타":30,"치킨":36,"스테이크":12,"샐러드":17,"스프":35,"스시":29,"타코":21,"부리토":27,"카레":19,"팟타이":27,"쌀국수":6,"딤섬":37,"만두":30,"교자":6,"춘권":37,"탕수육":16,"짜장면":5,"짬뽕":38,"마파두부":3,"오므라이스":15,"돈가스":23,"나폴리탄":5,"클램차우더":3,"아이스크림":7,"도넛":22,"쿠키":40,"파이":33,"과자":17,"젤리":18,"떡":9,"경단":2,"팥빙수":37,"호떡":13,"붕어빵":16,"타르트":10,"마카롱":28,"크루아상":30,"베이글":6,"머핀":39,"와플":25,"팬케이크":36,"크레페":14,"푸딩":14,"마시멜로":22,"된장":23,"간장":26,"고추장":10,"쌀":24,"밀가루":9,"설탕":26,"소금":38,"후추":11,"식초":25,"참기름":32,"들기름":13,"올리브유":17,"버터":19,"마요네즈":33,"케첩":31,"머스터드":10,"책":40,"음악":35,"영화":20,"게임":31,"여행":34,"운동":27,"요리":8,"그림":37,"사진":21,"드라마":32,"소설":29,"시":25,"춤":5,"노래":23,"악기":12,"연극":26,"뮤지컬":24,"콘서트":16,"전시":16,"독서":27,"글쓰기":31,"낚시":30,"캠핑":22,"등산":23,"수영":29,"달리기":37,"자전거":27,"요가":7,"명상":9,"테니스":15,"골프":29,"볼링":28,"배드민턴":14,"탁구":20,"당구":9,"포커":33,"체스":36,"바둑":33,"장기":26,"퍼즐":24,"보드게임":31,"레고":21,"모형":11,"수집":9,"만화":26,"웹툰":13,"애니메이션":33,"코딩":12,"블로그":27,"유튜브":24,"팟캐스트":30,"스트리밍":3,"독서모임":23,"피아노":36,"기타":40,"바이올린":39,"드럼":40,"플루트":38,"첼로":21,"트럼펫":36,"색소폰":8,"클라리넷":30,"하프":5,"우쿨렐레":20,"베이스":37,"신디사이저":35,"아코디언":15,"하모니카":21,"비파":30,"가야금":37,"거문고":32,"해금":14,"대금":9,"축구":15,"야구":13,"농구":35,"배구":8,"육상":28,"체조":23,"유도":26,"태권도":11,"권투":19,"레슬링":17,"씨름":15,"펜싱":26,"사격":37,"양궁":26,"다이빙":10,"서핑":10,"스키":5,"스노보드":29,"아이스하키":29,"피겨스케이팅":20,"마라톤":22,"철인3종":24,"트라이애슬론":8,"클라이밍":39,"격투기":36,"무술":19,"축구공":16,"야구방망이":11,"농구공":23,"배구공":12,"라켓":14,"골프채":25,"헬멧":12,"봄":35,"여름":11,"가을":38,"겨울":14,"아침":8,"점심":36,"저녁":16,"밤":7,"오전":23,"오후":10,"새벽":31,"황혼":29,"일출":20,"일몰":18,"주말":31,"평일":38,"월요일":24,"화요일":38,"수요일":20,"목요일":8,"금요일":24,"토요일":26,"일요일":37,"1월":12,"2월":5,"3월":16,"4월":24,"5월":23,"6월":6,"7월":20,"8월":10,"9월":18,"10월":6,"11월":12,"12월":21,"올해":33,"작년":31,"내년":34,"지금":24,"과거":9,"미래":6,"현재":30,"순간":21,"시간":28,"분":13,"초":24,"시대":14,"세기":21,"연대":21,"역사":12,"도시":58,"마을":83,"집":57,"학교":94,"회사":88,"병원":94,"공원":84,"시장":64,"주택":64,"아파트":90,"빌라":64,"오피스텔":83,"건물":64,"방":90,"거실":92,"부엌":67,"욕실":80,"침실":67,"베란다":92,"창문":80,"문":85,"계단":64,"엘리베이터":63,"주차장":83,"식당":67,"카페":66,"은행":85,"마트":88,"백화점":79,"도서관":88,"영화관":94,"공항":86,"역":84,"항구":84,"놀이터":73,"운동장":80,"수영장":68,"헬스장":68,"미용실":57,"체육관":79,"경기장":68,"박물관":62,"미술관":59,"과학관":1,"동물원":76,"식물원":90,"수족관":71,"놀이공원":95,"유원지":16,"캠프장":14,"야영장":2,"스키장":25,"골프장":16,"법원":92,"경찰서":82,"소방서":57,"우체국":83,"세무서":2,"구청":12,"시청":79,"국회":14,"대사관":3,"호텔":81,"모텔":18,"민박":12,"게스트하우스":4,"리조트":60,"펜션":94,"자동차":30,"기차":12,"비행기":10,"버스":19,"지하철":20,"택시":39,"오토바이":15,"트럭":13,"도로":11,"신호등":30,"교통":27,"운전":16,"고속도로":7,"터널":15,"교량":26,"육교":37,"횡단보도":39,"주유소":31,"세차장":16,"정류장":29,"플랫폼":36,"헬기":34,"열기구":19,"드론":9,"유람선":32,"페리":25,"잠수함":8,"수상스키":21,"킥보드":26,"전동차":18,"케이블카":25,"모노레일":3,"트램":21,"컴퓨터":24,"스마트폰":23,"카메라":25,"텔레비전":35,"냉장고":16,"세탁기":31,"에어컨":5,"시계":15,"노트북":12,"태블릿":17,"이어폰":35,"스피커":31,"충전기":22,"키보드":18,"마우스":21,"프린터":40,"스캐너":9,"모니터":25,"라우터":15,"서버":10,"클라우드":19,"인터넷":22,"와이파이":12,"블루투스":18,"USB":23,"하드디스크":21,"메모리":7,"배터리":7,"전원":3,"소프트웨어":27,"앱":21,"프로그램":18,"인공지능":9,"로봇":5,"스마트워치":16,"VR기기":12,"게임기":17,"콘솔":24,"믹서":13,"전자레인지":6,"밥솥":36,"청소기":9,"공기청정기":25,"가습기":32,"제습기":1,"빨간색":7,"파란색":20,"노란색":34,"초록색":20,"보라색":30,"주황색":13,"흰색":38,"검은색":35,"분홍색":38,"하늘색":22,"갈색":22,"회색":32,"금색":27,"은색":34,"베이지":39,"청록색":12,"연두색":18,"자주색":27,"남색":16,"진홍색":31,"주홍색":17,"올리브색":12,"민트색":8,"코랄색":31,"라벤더색":5,"아이보리":31,"카키색":33,"머스터드색":3,"가족":26,"친구":5,"부모":17,"어머니":35,"아버지":5,"형제":37,"자매":6,"아이":27,"할머니":24,"할아버지":34,"아들":7,"딸":19,"남편":10,"아내":16,"선생님":25,"학생":35,"의사":36,"간호사":38,"경찰":19,"소방관":16,"요리사":39,"운전기사":22,"배우":31,"가수":17,"직장":5,"동료":24,"상사":37,"사장":19,"직원":16,"이웃":25,"손님":30,"친척":32,"연인":38,"애인":17,"파트너":38,"짝":12,"스승":27,"제자":6,"선배":34,"후배":37,"지인":4,"낯선사람":23,"외국인":1,"노인":13,"어른":16,"청년":40,"청소년":24,"어린이":36,"변호사":16,"교사":36,"약사":25,"한의사":9,"치과의사":20,"수의사":35,"엔지니어":30,"개발자":13,"디자이너":23,"기획자":7,"마케터":24,"영업자":5,"회계사":38,"건축가":18,"인테리어":3,"조경사":21,"경찰관":11,"군인":14,"공무원":27,"기자":32,"아나운서":33,"작가":6,"시인":25,"화가":38,"조각가":6,"사진작가":20,"댄서":39,"코미디언":31,"감독":36,"작곡가":28,"프로듀서":18,"파티시에":35,"바리스타":11,"소믈리에":19,"웨이터":11,"셰프":9,"농부":17,"어부":34,"목수":18,"용접공":7,"배관공":24,"전기기사":11,"미용사":9,"택배기사":20,"버스기사":1,"파일럿":39,"선장":22,"기관사":2,"코":28,"입":30,"귀":13,"손":35,"발":22,"머리":21,"얼굴":7,"팔":32,"다리":25,"등":21,"어깨":24,"목":31,"허리":12,"가슴":9,"심장":16,"뇌":32,"뼈":6,"근육":35,"피부":20,"머리카락":23,"손가락":18,"발가락":35,"손목":26,"발목":15,"무릎":39,"팔꿈치":33,"손바닥":11,"발바닥":32,"눈썹":12,"속눈썹":20,"이마":22,"턱":12,"뺨":15,"광대":19,"코끝":13,"입술":25,"잇몸":5,"혀":18,"폐":23,"간":22,"위":29,"신장":11,"방광":5,"췌장":10,"비장":18,"척추":5,"혈관":32,"신경":22,"혈액":12,"림프":7,"호르몬":21,"세포":14,"유전자":14,"티셔츠":5,"셔츠":13,"블라우스":12,"바지":11,"청바지":23,"반바지":10,"치마":35,"원피스":26,"재킷":28,"코트":11,"점퍼":26,"패딩":9,"니트":5,"가디건":20,"조끼":18,"정장":23,"넥타이":5,"벨트":15,"양말":15,"스타킹":21,"신발":28,"운동화":31,"구두":24,"샌들":15,"슬리퍼":19,"부츠":34,"모자":10,"베레모":11,"야구모자":3,"선글라스":27,"안경":40,"가방":35,"백팩":24,"핸드백":27,"지갑":8,"반지":27,"목걸이":12,"팔찌":13,"귀걸이":14,"장갑":38,"스카프":31,"머플러":17,"수영복":19,"잠옷":6,"속옷":16,"양복":36,"수학":13,"영어":9,"국어":23,"과학":17,"지리":7,"철학":9,"심리학":31,"경제학":18,"사회학":37,"문학":5,"물리":27,"화학":6,"생물":38,"지구과학":25,"천문학":8,"의학":36,"법학":19,"경영학":22,"교육학":38,"언어학":34,"통계학":12,"컴퓨터공학":18,"건축학":36,"예술학":20,"음악학":1,"체육학":14,"영양학":25,"환경학":4,"교과서":22,"노트":22,"연필":29,"볼펜":11,"지우개":29,"자":18,"컴퍼스":8,"가위":33,"테이프":25,"책상":29,"칠판":1,"분필":21,"시험":30,"숙제":7,"업무":29,"회의":19,"출근":22,"퇴근":25,"야근":19,"월급":21,"보너스":12,"휴가":7,"프로젝트":23,"기획":9,"보고서":34,"발표":26,"브레인스토밍":9,"마감":32,"납기":17,"계약":30,"협상":22,"제안서":2,"견적":9,"인보이스":23,"결재":2,"승인":7,"반려":3,"채용":33,"면접":15,"이력서":34,"자기소개서":24,"인턴":33,"신입":33,"경력":27,"정치":40,"경제":37,"사회":40,"문화":16,"기술":9,"예술":6,"민주주의":34,"자본주의":10,"사회주의":13,"공산주의":12,"자유주의":1,"보수주의":21,"선거":17,"투표":10,"정부":7,"대통령":32,"총리":8,"장관":25,"국회의원":8,"세금":35,"복지":25,"의료":15,"교육":22,"안보":38,"외교":11,"통일":10,"법":40,"헌법":11,"형법":18,"민법":20,"재판":37,"검사":25,"판사":15,"환경":13,"기후":2,"온난화":16,"탄소":23,"오염":25,"재활용":14,"에너지":30,"태양광":6,"풍력":13,"수력":5,"원자력":3,"화석연료":8,"석유":14,"천연가스":3,"석탄":2,"생태계":21,"생물다양성":8,"멸종":2,"보존":22,"복원":16,"산림":2,"해양":24,"대기":5,"레스토랑":4,"패스트푸드":2,"뷔페":7,"포장마차":22,"분식점":13,"술집":5,"바":13,"베이커리":17,"아이스크림가게":6,"편의점":3,"슈퍼마켓":23,"공":12,"골대":6,"바둑판":21,"장기판":9,"체스판":25,"주사위":18,"카드":17,"블록":10,"퍼즐조각":17,"인형":8,"장난감":25,"조이스틱":20,"소파":29,"침대":21,"의자":25,"옷장":29,"서랍장":6,"선반":35,"테이블":36,"식탁":12,"커튼":12,"카펫":15,"러그":35,"조명":39,"샹들리에":19,"화분":9,"액자":12,"거울":8,"전화기":9,"팩스":6,"달력":37,"메모판":18,"수건":12,"이불":25,"베개":34,"담요":14,"쿠션":7,"칫솔":20,"치약":39,"비누":35,"샴푸":22,"린스":24,"로션":25,"선크림":17,"화장품":22,"향수":27,"면도기":27,"드라이어":17,"빗":20,"헤어핀":8,"고무줄":23,"손거울":17,"세면대":6,"변기":21,"욕조":18,"샤워기":5,"냄비":19,"프라이팬":15,"그릇":23,"컵":12,"접시":17,"젓가락":32,"숟가락":35,"포크":15,"칼":20,"도마":14,"개수대":18,"주전자":31,"커피메이커":21,"토스터":22,"오븐":10,"장미":27,"튤립":39,"국화":5,"해바라기":13,"벚꽃":20,"개나리":16,"진달래":35,"수선화":34,"라벤더":24,"카네이션":13,"백합":21,"아이리스":8,"모란":35,"작약":15,"코스모스":15,"선인장":32,"대나무":30,"소나무":18,"참나무":35,"단풍나무":33,"은행나무":30,"자작나무":14,"야자나무":24,"올리브나무":12,"뽕나무":18,"감나무":21,"사과나무":21,"배나무":9,"잔디":17,"이끼":15,"고사리":13,"양치류":10,"해조류":25,"매화":37,"오동나무":21,"건강":9,"질병":8,"감기":36,"독감":20,"코로나":19,"암":18,"당뇨":31,"고혈압":14,"심장병":14,"뇌졸중":13,"골절":3,"염좌":3,"알레르기":13,"아토피":17,"천식":13,"수술":23,"치료":24,"약":11,"주사":26,"진단":9,"처방":39,"입원":30,"재활":33,"물리치료":17,"한방":7,"침":10,"한약":6,"예방접종":19,"마스크":30,"혈압":29,"혈당":38,"체온":5,"맥박":17,"호흡":14,"면역":15,"전화":14,"문자":17,"이메일":32,"카카오톡":21,"인스타그램":7,"페이스북":6,"트위터":8,"틱톡":7,"넷플릭스":3,"라디오":28,"신문":12,"잡지":8,"뉴스":29,"광고":34,"방송":30,"채널":13,"콘텐츠":40,"돈":38,"저축":32,"투자":24,"주식":25,"부동산":14,"펀드":35,"보험":22,"대출":20,"현금":33,"계좌":37,"이자":6,"이윤":16,"손실":35,"예산":21,"지출":28,"수입":30,"부채":18,"자산":21,"환율":28,"물가":33,"인플레이션":21,"경기":37,"불황":32,"호황":11,"성장":30,"발전":37,"번영":10,"적자":22,"흑자":1,"관광":1,"숙소":1,"비행기표":3,"여권":40,"짐":14,"캐리어":31,"지도":12,"관광지":27,"명소":18,"유적지":33,"쇼핑":12,"음식투어":2,"맛집":6,"카페투어":1,"기념품":30,"환전":10,"한복":20,"한옥":38,"한식":1,"풍물":28,"사물놀이":31,"제기차기":8,"팽이":8,"연날리기":12,"강강술래":17,"판소리":11,"전통춤":6,"탈춤":6,"장승":16,"솟대":7,"토우":2,"도자기":35,"단오":33,"추석":8,"설날":36,"정월대보름":9,"동지":34,"K팝":14,"한류":24,"아이돌":25,"먹방":20,"BTS":19,"방탄소년단":18,"블랙핑크":9,"방탄":23,"SM":17,"JYP":6,"YG":16,"한국":40,"미국":32,"일본":22,"중국":30,"영국":27,"프랑스":37,"독일":11,"이탈리아":38,"스페인":34,"러시아":10,"캐나다":7,"호주":21,"인도":31,"브라질":15,"멕시코":24,"태국":15,"베트남":12,"인도네시아":8,"필리핀":4,"싱가포르":8,"말레이시아":21,"서울":9,"부산":37,"제주":26,"인천":39,"대구":35,"광주":9,"대전":11,"울산":13,"도쿄":27,"뉴욕":40,"런던":11,"파리":12,"베이징":26,"상하이":16,"홍콩":15,"방콕":30,"우주":22,"지구":14,"태양계":29,"은하":7,"블랙홀":40,"행성":15,"위성":21,"혜성":33,"소행성":22,"중력":10,"빛":24,"공간":4,"물질":11,"원자":22,"분자":18,"전자":15,"양성자":13,"중성자":18,"힉스입자":7,"양자역학":9,"상대성이론":7,"종교":15,"불교":7,"기독교":20,"이슬람":27,"유교":23,"도교":17,"힌두교":17,"신":11,"기도":17,"깨달음":27,"진리":19,"선":20,"악":14,"윤리":32,"도덕":19,"가치":38,"의미":27,"목적":18,"존재":37,"의식":14,"자아":39,"날씨":6,"온도":20,"계획":35,"약속":18,"기억":27,"생각":5,"느낌":14,"경험":26,"습관":40,"취미":12,"목표":38,"성공":31,"실패":5,"도전":24,"변화":39,"결정":27,"선택":40,"행동":22,"결과":13,"원인":23,"이유":28,"방법":30,"과정":24,"시작":24,"끝":16,"중간":16,"처음":18,"마지막":17,"반복":31,"패턴":39,"규칙":35,"광장":9,"골목":11,"지하":12,"지상":6,"지붕":10,"벽":10,"바닥":30,"천장":17,"기둥":23,"난간":19,"발코니":6,"테라스":37,"정원":21,"마당":26,"창고":34}